beecol/__init__.py
beecol/base.py
beecol-0.1.0.dist-info/LICENSE
beecol-0.1.0.dist-info/METADATA
beecol-0.1.0.dist-info/WHEEL
beecol-0.1.0.dist-info/top_level.txt
beecol-0.1.0.dist-info/RECORD
