Metadata-Version: 2.1
Name: beecol
Version: 0.1.0
Summary: A simple Artificial Bee Colony (ABC) library for Python.
Home-page: https://github.com/atasoglu/beecol
Author: Ahmet Atasoglu
Author-email: ahmetatasoglu98@gmail.com
License: MIT
Classifier: Programming Language :: Python :: 3
Classifier: Topic :: Scientific/Engineering :: Artificial Intelligence
Classifier: License :: OSI Approved :: MIT License
Classifier: Operating System :: OS Independent
Requires-Python: >=3.6
License-File: LICENSE
Requires-Dist: numpy
